pyrxing-0.4.3.dist-info/METADATA
pyrxing-0.4.3.dist-info/WHEEL
pyrxing/__init__.py
pyrxing/__init__.pyi
pyrxing/py.typed
pyrxing/pyrxing.cpython-312-x86_64-linux-gnu.so
pyrxing-0.4.3.dist-info/RECORD
