Metadata-Version: 2.4
Name: pyrxing
Version: 0.4.3
Classifier: Programming Language :: Rust
Classifier: Programming Language :: Python :: 3
Classifier: Programming Language :: Python :: 3.11
Classifier: Programming Language :: Python :: 3.12
Classifier: Programming Language :: Python :: 3.13
Classifier: Programming Language :: Python :: 3.14
Classifier: Programming Language :: Python :: Implementation :: CPython
Classifier: License :: OSI Approved :: Apache Software License
Summary: A barcode reader extension module using zxing-cpp and pyo3
Keywords: barcode,qr-code,scanner,decoder,zxing,computer-vision,image-processing,rust,alpine
Author-email: Takanobu Nagumo <nagumo5683@gmail.com>
License: Apache-2.0
Requires-Python: >=3.11
Project-URL: Homepage, https://github.com/tanagumo/pyrxing
